mcp_query_table/__init__.py
mcp_query_table/__main__.py
mcp_query_table/_version.py
mcp_query_table/enums.py
mcp_query_table/server.py
mcp_query_table/tool.py
mcp_query_table/utils.py
mcp_query_table/providers/__init__.py
mcp_query_table/providers/baidu.py
mcp_query_table/providers/n.py
mcp_query_table/providers/yuanbao.py
mcp_query_table/sites/__init__.py
mcp_query_table/sites/eastmoney.py
mcp_query_table/sites/iwencai.py
mcp_query_table/sites/tdx.py
mcp_query_table-0.3.10.dist-info/METADATA
mcp_query_table-0.3.10.dist-info/WHEEL
mcp_query_table-0.3.10.dist-info/licenses/LICENSE
mcp_query_table-0.3.10.dist-info/RECORD
