Metadata-Version: 2.4
Name: mcp_query_table
Version: 0.3.10
Summary: query table from website, support MCP
Author-email: wukan <wu-kan@163.com>
License: MIT License
License-File: LICENSE
Keywords: eastmoney,iwencai,mcp,playwright,table,tdx
Classifier: Development Status :: 4 - Beta
Classifier: Programming Language :: Python
Requires-Python: >=3.10
Requires-Dist: loguru
Requires-Dist: mcp
Requires-Dist: pandas
Requires-Dist: playwright
Requires-Dist: playwright-stealth>=2.0.0
Requires-Dist: tabulate
